pydb/__init__.py
pydb/database.py
pyjcli_beta-1.0.0.dist-info/METADATA
pyjcli_beta-1.0.0.dist-info/WHEEL
pyjcli_beta-1.0.0.dist-info/entry_points.txt
pyjcli_beta-1.0.0.dist-info/top_level.txt
pyjcli_beta-1.0.0.dist-info/RECORD
