Metadata-Version: 2.4
Name: pyjcli-beta
Version: 1.0.0
Summary: A simple JSON-based CLI database tool
Home-page: https://github.com/punitsinha23/pydb
Author: Punit Sinha
Classifier: Programming Language :: Python :: 3
Classifier: License :: OSI Approved :: MIT License
Requires-Python: >=3.6
Dynamic: author
Dynamic: classifier
Dynamic: description-content-type
Dynamic: home-page
Dynamic: requires-python
Dynamic: summary
